{
  "type": "minecraft:crafting_shaped",
  "category": "equipment",
  "key": {
    "D": {
      "item": "minecraft:diamond"
    },
    "G": {
      "item": "minecraft:gold_ingot"
    },
    "M": {
      "item": "lovely_sparkle_pieces:minigun"
    },
    "N": {
      "item": "minecraft:netherite_ingot"
    },
    "R": {
      "item": "minecraft:redstone_block"
    }
  },
  "pattern": [
    "NNN",
    "RDR",
    "GMG"
  ],
  "result": {
    "count": 1,
    "id": "lovely_sparkle_pieces:hkmp7"
  }
}