{
  "type": "lovely_sparkle_pieces:curio_work",
  "primary": {
    "item": "minecraft:gold_ingot"
  },
  "result": {
    "count": 1,
    "id": "lovely_sparkle_pieces:ring_of_favor_and_protection"
  },
  "secondary": [
    {
      "item": "minecraft:iron_ingot"
    },
    {
      "item": "minecraft:iron_ingot"
    },
    {
      "item": "minecraft:redstone"
    },
    {
      "item": "minecraft:redstone"
    },
    {
      "item": "minecraft:lapis_lazuli"
    },
    {
      "item": "minecraft:glowstone_dust"
    },
    {
      "item": "lovely_sparkle_pieces:moon_ingot"
    },
    {
      "item": "minecraft:diamond"
    }
  ]
}