{
  "type": "lovely_sparkle_pieces:curio_work",
  "primary": {
    "item": "minecraft:compass"
  },
  "result": {
    "count": 1,
    "id": "lovely_sparkle_pieces:position_tracker"
  },
  "secondary": [
    {
      "item": "minecraft:paper"
    },
    {
      "item": "minecraft:redstone"
    },
    {
      "item": "minecraft:copper_ingot"
    },
    {
      "item": "minecraft:glowstone_dust"
    },
    {
      "item": "lovely_sparkle_pieces:moon_ingot"
    },
    {
      "item": "minecraft:iron_ingot"
    }
  ]
}